tk_apis/__init__.py
tk_apis/moz_calls.py
tk_apis/semrush_calls.py
tk_apis/serpapi_calls.py
tk_apis/tkds_calls.py
tk_apis-0.3.1.dist-info/LICENSE
tk_apis-0.3.1.dist-info/METADATA
tk_apis-0.3.1.dist-info/WHEEL
tk_apis-0.3.1.dist-info/top_level.txt
tk_apis-0.3.1.dist-info/RECORD
