Metadata-Version: 2.1
Name: tk-apis
Version: 0.3.1
Summary: Wrappers for some common SERP ingestion APIs we use at TK
Home-page: https://github.com/terakeet/tk_apis
Author: Jennifer Brussow
Author-email: jbrussow@terakeet.com
Project-URL: Bug Tracker, https://github.com/terakeet/tk_apis/issues
Classifier: Programming Language :: Python :: 3
Classifier: License :: OSI Approved :: MIT License
Classifier: Operating System :: OS Independent
Requires-Python: >=3.6
License-File: LICENSE
Requires-Dist: requests (==2.27.1)
Requires-Dist: google-search-results
Requires-Dist: pandas (==1.4.2)
Requires-Dist: numpy (==1.22.3)
